reahl/mailutil/__init__.py
reahl/mailutil/mail.py
reahl/mailutil/reusableconfig.py
reahl/mailutil/rst.py
reahl/mailutil_dev/__init__.py
reahl/mailutil_dev/test_mail.py
reahl_mailutil-7.0.3.dist-info/LICENSE
reahl_mailutil-7.0.3.dist-info/METADATA
reahl_mailutil-7.0.3.dist-info/WHEEL
reahl_mailutil-7.0.3.dist-info/reahl-component.toml
reahl_mailutil-7.0.3.dist-info/top_level.txt
reahl_mailutil-7.0.3.dist-info/RECORD
